waffleweb/__init__.py
waffleweb/app.py
waffleweb/cookie.py
waffleweb/datatypes.py
waffleweb/defaults.py
waffleweb/errorResponses.py
waffleweb/exceptions.py
waffleweb/files.py
waffleweb/middleware.py
waffleweb/parser.py
waffleweb/project.py
waffleweb/request.py
waffleweb/response.py
waffleweb/static.py
waffleweb/template.py
waffleweb/wsgi.py
waffleweb-0.1a4.dist-info/LICENSE
waffleweb-0.1a4.dist-info/METADATA
waffleweb-0.1a4.dist-info/WHEEL
waffleweb-0.1a4.dist-info/top_level.txt
waffleweb-0.1a4.dist-info/RECORD
