Metadata-Version: 2.1
Name: waffleweb
Version: 0.1a4
Summary: A python library for making scalable websites easy
Home-page: https://berserkware.github.io/waffleweb
Author: Caleb Mckay
Author-email: berserkware@gmail.com
License: MIT
Project-URL: Documentation, https://waffleweb.readthedocs.io
Project-URL: Source Code, https://github.com/Berserkware/waffleweb
Project-URL: Discord, https://discord.gg/U6HjwhkcGr
Keywords: framework,web,wsgi,waffleweb,web-framework
Platform: UNKNOWN
Classifier: Intended Audience :: Developers
Classifier: License :: OSI Approved :: MIT License
Classifier: Programming Language :: Python :: 3
Classifier: Programming Language :: Python :: 3.9
Classifier: Programming Language :: Python :: 3.10
Requires-Python: >=3.9
Requires-Dist: jinja2
Requires-Dist: pytz
